{
  "command": [
    {
      "name": "User Joins Server",
      "perms": [],
      "actions": [
        {
          "name": "Joint",
          "category": "Message",
          "type": "Send Direct Message",
          "user": "%%newuser%%",
          "messagetext": "Welcome to $$ServerName$$ $$ServerIcon$$ Thank you for joining you are the member count is now $$MemberCount$$ Thank you and enjoy your stay!"
        }
      ],
      "var": {
        "user": "newuser"
      }
    },
    {
      "name": "Any Message",
      "perms": [],
      "actions": [],
      "var": {
        "user": "msguser"
      }
    },
    {
      "name": "User Kicked",
      "perms": [],
      "actions": [],
      "var": {
        "user": "kicked"
      }
    },
    {
      "name": "User Banned",
      "perms": [],
      "actions": [],
      "var": {
        "user": "banuser"
      }
    },
    {
      "name": "Bot Initialization",
      "perms": [],
      "actions": [],
      "var": {}
    }
  ]
}